docsplice/__init__.py
docsplice/splice.py
docsplice-0.2.0.dist-info/LICENSE
docsplice-0.2.0.dist-info/METADATA
docsplice-0.2.0.dist-info/WHEEL
docsplice-0.2.0.dist-info/top_level.txt
docsplice-0.2.0.dist-info/RECORD
