Metadata-Version: 2.1
Name: docsplice
Version: 0.2.0
Summary: Docstring splicing for python functions 🧬
Author-email: Hannes Breytenbach <hannes@saao.ac.za>
License: MIT
Project-URL: Homepage, https://github.com/astromancer/docsplice
Project-URL: Bug Tracker, https://github.com/astromancer/docsplice/issues
Classifier: Topic :: Documentation
Classifier: Topic :: Software Development :: Libraries :: Python Modules
Classifier: Development Status :: 3 - Alpha
Classifier: Intended Audience :: Developers
Classifier: License :: OSI Approved :: MIT License
Classifier: Programming Language :: Python :: 3.8
Requires-Python: >=3.8
License-File: LICENSE
Provides-Extra: tests
Requires-Dist: pytest ; extra == 'tests'
